shimtax/__init__.py
shimtax/_core.py
shimtax/_pth.py
shimtax/_tests/__init__.py
shimtax/_tests/conftest.py
shimtax/_tests/encodings/aaa_to_bbb.py
shimtax/_tests/encodings/ccc_to_ddd.py
shimtax/_tests/encodings/test_encodings.py
shimtax/_tests/test_core.py
shimtax/cli.py
shimtax/conftest.py
shimtax/errors.py
shimtax/py.typed
shimtax-0.1.dist-info/entry_points.txt
shimtax-0.1.dist-info/LICENSE
shimtax-0.1.dist-info/WHEEL
shimtax-0.1.dist-info/METADATA
shimtax-0.1.dist-info/RECORD
