Metadata-Version: 2.1
Name: shimtax
Version: 0.1
Summary: A pluggable manager for syntax rewriting codecs
Home-page: https://github.com/altendky/shimtax/
License: MIT-0
Keywords: codec,plugin,shim,syntax
Author: Kyle Altendorf
Author-email: sda@fstab.net
Requires-Python: >=3.7,<4
Classifier: License :: Other/Proprietary License
Classifier: Programming Language :: Python :: 3
Classifier: Programming Language :: Python :: 3.7
Classifier: Programming Language :: Python :: 3.8
Classifier: Programming Language :: Python :: 3.9
Classifier: Programming Language :: Python :: 3.10
Provides-Extra: build
Provides-Extra: checks
Provides-Extra: coverage
Provides-Extra: dev
Provides-Extra: test
Requires-Dist: attrs (>=21.3.0)
Requires-Dist: black (>=22.8.0); extra == "checks" or extra == "dev"
Requires-Dist: build (>=0.5.0); extra == "build"
Requires-Dist: click (>=8.1.3,<9.0.0)
Requires-Dist: coverage (>=6.4.4,<7.0.0); extra == "coverage"
Requires-Dist: isort (>=5.10.1); extra == "checks" or extra == "dev"
Requires-Dist: mypy (>=0.971); extra == "checks" or extra == "dev"
Requires-Dist: pytest (>=7.1.3,<8.0.0); extra == "checks" or extra == "dev" or extra == "test"
Requires-Dist: pytest-cov (>=3.0.0,<4.0.0); extra == "dev" or extra == "test"
Requires-Dist: setuptools (>=52)
Requires-Dist: twine (>=4.0.1,<5.0.0); extra == "build"
Project-URL: Source, https://github.com/altendky/shimtax/
